DataClasses/__init__.py
DataClasses/sport_event.py
Modules/__init__.py
Modules/sport_event.py
Modules/sport_filter.py
Utils/__init__.py
Utils/k8s.py
Utils/logging.py
Utils/webscraper.py
r0p3/__init__.py
r0p3/Modules/__init__.py
r0p3/Modules/free_games.py
r0p3/Modules/sport_event.py
r0p3/Modules/sport_filter.py
r0p3/Utils/__init__.py
r0p3/Utils/k8s.py
r0p3/Utils/logging.py
r0p3/Utils/utc_to_swedish_time.py
r0p3/Utils/webscraper.py
r0p3-0.0.25.dist-info/LICENSE
r0p3-0.0.25.dist-info/METADATA
r0p3-0.0.25.dist-info/WHEEL
r0p3-0.0.25.dist-info/top_level.txt
r0p3-0.0.25.dist-info/RECORD
