Metadata-Version: 2.1
Name: r0p3
Version: 0.0.25
Summary: Utilies module for r0p3 by r0p3
Author: r0p3
Author-email: <robin.pettersson.96@gmail.com>
Keywords: r0p3
Classifier: Programming Language :: Python :: 3
License-File: LICENSE
Requires-Dist: selenium
Requires-Dist: pytz
Requires-Dist: kubernetes
Requires-Dist: requests
Requires-Dist: beautifulsoup4
Requires-Dist: dataclasses
